{
"__signature": "@generated SignedSource<<70c4a163ae0b2c2b4ab1708ad88110d0>>",
"__generatedBy": "export-localized-js-module.php",
"countries": {
"US": "ארצות הברית",
"CA": "קנדה",
"GB": "בריטניה",
"AR": "ארגנטינה",
"AU": "אוסטרליה",
"AT": "אוסטריה",
"BE": "בלגיה",
"BR": "ברזיל",
"CL": "צ'ילה",
"CN": "סין",
"CO": "קולומביה",
"HR": "קרואטיה",
"DK": "דנמרק",
"DO": "הרפובליקה הדומיניקנית",
"EG": "מצרים",
"FI": "פינלנד",
"FR": "צרפת",
"DE": "גרמניה",
"GR": "יוון",
"HK": "הונג קונג",
"IN": "הודו",
"ID": "אינדונזיה",
"IE": "אירלנד",
"IL": "ישראל",
"IT": "איטליה",
"JP": "יפן",
"JO": "ירדן",
"KW": "כווית",
"LB": "לבנון",
"MY": "מלזיה",
"MX": "מקסיקו",
"NL": "הולנד",
"NZ": "ניו זילנד",
"NG": "ניגריה",
"NO": "נורבגיה",
"PK": "פקיסטן",
"PA": "פנמה",
"PE": "פרו",
"PH": "פיליפינים",
"PL": "פולין",
"RU": "רוסיה",
"SA": "ערב הסעודית",
"RS": "סרביה",
"SG": "סינגפור",
"ZA": "דרום אפריקה",
"KR": "קוריאה הדרומית",
"ES": "ספרד",
"SE": "שבדיה",
"CH": "שווייץ",
"TW": "טיוואן",
"TH": "תאילנד",
"TR": "טורקיה",
"AE": "איחוד האמירויות הערביות",
"VE": "ונצואלה",
"PT": "פורטוגל",
"LU": "לוקסמבורג",
"BG": "בולגריה",
"CZ": "צ'כיה",
"SI": "סלובניה",
"IS": "איסלנד",
"SK": "סלובקיה",
"LT": "ליטא",
"TT": "טרינידד וטובגו",
"BD": "בנגלדש",
"LK": "סרי לנקה",
"KE": "קניה",
"HU": "הונגריה",
"MA": "מרוקו",
"CY": "קפריסין",
"JM": "ג'מייקה",
"EC": "אקוודור",
"RO": "רומניה",
"BO": "בוליביה",
"GT": "גואטמלה",
"CR": "קוסטה ריקה",
"QA": "קטאר",
"SV": "אל סלוודור",
"HN": "הונדורס",
"NI": "ניקרגואה",
"PY": "פרגוואי",
"UY": "אורוגוואי",
"PR": "פורטו ריקו",
"BA": "בוסניה והרצגובינה",
"PS": "פלסטין",
"TN": "תוניסיה",
"BH": "בחריין",
"VN": "וייטנאם",
"GH": "גאנה",
"MU": "מאוריציוס",
"UA": "אוקראינה",
"MT": "מלטה",
"BS": "איי בהאמה",
"MV": "האיים המלדיביים",
"OM": "עומאן",
"MK": "מקדוניה",
"LV": "לטביה",
"EE": "אסטוניה",
"IQ": "עיראק",
"DZ": "אלג'יריה",
"AL": "אלבניה",
"NP": "נפאל",
"MO": "מאקאו",
"ME": "מונטנגרו",
"SN": "סנגל",
"GE": "גיאורגיה",
"BN": "ברוניי",
"UG": "אוגנדה",
"GP": "גוואדלופ",
"BB": "ברבדוס",
"AZ": "אזרבייג'ן",
"TZ": "טנזניה",
"LY": "לוב",
"MQ": "מרטיניק",
"CM": "קמרון",
"BW": "בוטסואנה",
"ET": "אתיופיה",
"KZ": "קזחסטן",
"NA": "נמיביה",
"MG": "מדגסקר",
"NC": "קלדוניה החדשה",
"MD": "מולדובה",
"FJ": "פיג'י",
"BY": "בלרוס",
"JE": "ג'רזי",
"GU": "גואם",
"YE": "תימן",
"ZM": "זמביה",
"IM": "האי מאן",
"HT": "האיטי",
"KH": "קמבודיה",
"AW": "ארובה",
"PF": "פולינזיה הצרפתית",
"AF": "אפגניסטן",
"BM": "ברמודה",
"GY": "גיאנה",
"AM": "ארמניה",
"MW": "מלאווי",
"AG": "אנטיגואה",
"RW": "רואנדה",
"GG": "גרנזי",
"GM": "גמביה",
"FO": "איי פארו",
"LC": "סנט לוסיה",
"KY": "איי קיימן",
"BJ": "בנין",
"AD": "אנדורה",
"GD": "גרנדה",
"VI": "איי הבתולה של ארה\"ב",
"BZ": "בליז",
"VC": "סנט וינסנט והגרנדינים",
"MN": "מונגוליה",
"MZ": "מוזמביק",
"ML": "מאלי",
"AO": "אנגולה",
"GF": "גיאנה הצרפתית",
"UZ": "אוזבקיסטן",
"DJ": "ג'יבוטי",
"BF": "בורקינה פאסו",
"MC": "מונקו",
"TG": "טוגו",
"GL": "גרינלנד",
"GA": "גבון",
"GI": "גיברלטר",
"CD": "הרפובליקה הדמוקרטית של קונגו",
"KG": "קירגיסטן",
"PG": "פפואה גינאה החדשה",
"BT": "בהוטן",
"KN": "סנט קיטס ונוויס",
"SZ": "סווזילנד",
"LS": "לסותו",
"LA": "לאוס",
"LI": "ליכטנשטיין",
"MP": "איי מריאנה הצפוניים",
"SR": "סורינם",
"SC": "איי סיישל",
"VG": "איי הבתולה הבריטיים",
"TC": "איי טורקס וקאיקוס",
"DM": "דומיניקה",
"MR": "מאוריטניה",
"AX": "איי אלנד",
"SM": "סן מרינו",
"SL": "סיירה לאונה",
"NE": "ניז'ר",
"CG": "הרפובליקה של קונגו",
"AI": "אנגווילה",
"YT": "מיוטה",
"CV": "כף ורדה",
"GN": "גינאה",
"TM": "טורקמניסטן",
"BI": "בורונדי",
"TJ": "טג'יקיסטן",
"VU": "ונואטו",
"SB": "איי שלמה",
"ER": "אריתריאה",
"WS": "סמואה",
"AS": "סמואה האמריקנית",
"FK": "איי פוקלנד",
"GQ": "גינאה המשוונית",
"TO": "טונגה",
"KM": "איי קומורו",
"PW": "פלאו",
"FM": "מיקרונזיה",
"CF": "הרפובליקה המרכז-אפריקאית",
"SO": "סומליה",
"MH": "איי מרשל",
"VA": "ותיקן",
"TD": "צ'אד",
"KI": "קיריבטי",
"ST": "סאו טומה ופרינסיפה",
"TV": "טובאלו",
"NR": "נאורו",
"RE": "ראוניון",
"LR": "ליבריה",
"ZW": "זימבבואה",
"CI": "חוף השנהב",
"MM": "מיאנמר",
"AN": "האנטילים ההולנדיים",
"AQ": "אנטארקטיקה",
"BQ": "בונייר, סנט אוסטטיוס וסאבא",
"BV": "האי בובה",
"IO": "הטריטוריה הבריטית באוקיינוס ההודי",
"CX": "אי חג המולד",
"CC": "איי קוקוס (קילינג)",
"CK": "איי קוק",
"CW": "קורסאו",
"TF": "השטחים הדרומיים של צרפת",
"GW": "גינאה ביסאו",
"HM": "האי הרד ואיי מקדונלד",
"XK": "קוסובו",
"MS": "מונסראט",
"NU": "ניואה",
"NF": "האי נורפוק",
"KP": "קוריאה הצפונית",
"PN": "פיטקרן",
"BL": "סן ברתלמי",
"SH": "סנט הלנה",
"MF": "סנט מרטין",
"PM": "סן פייר ומיקלון",
"SX": "סנט מארטן",
"GS": "איי ג'ורג'יה הדרומית ואיי סנדוויץ' הדרומיים",
"SS": "דרום סודן",
"SJ": "סבאלברד ויאן מאיין",
"TL": "מזרח טימור",
"TK": "טוקלאו",
"UM": "איים קטנים הסמוכים לארצות הברית",
"WF": "ואליס ופוטונה",
"EH": "סהרה המערבית"
},
"countriesWithCities": [
"US",
"GB",
"CA",
"AU",
"FR",
"ES",
"IT",
"SW",
"NO",
"DK",
"DE",
"BE",
"VE",
"TR",
"CO",
"FI",
"JP",
"CL",
"CH",
"AR",
"SE",
"NL",
"LE",
"PT",
"GR",
"NZ",
"IE",
"ID",
"MY",
"TH",
"VN",
"PL",
"CZ",
"RO",
"RS",
"BO",
"BR",
"CR",
"DO",
"EC",
"SV",
"GT",
"HN",
"MX",
"NI",
"PA",
"PY",
"PE",
"PR",
"UY",
"AT",
"IL",
"IN",
"TW",
"RU",
"ES",
"EG",
"SA",
"AE",
"AT",
"CH",
"PH",
"ZA",
"KR",
"UA",
"BG",
"HU",
"NG"
],
"countriesWithRegions": [
"US",
"CA",
"AU",
"GB",
"JP",
"ES",
"BR",
"IN",
"FR",
"DE",
"MX",
"AR",
"CO",
"KR",
"TH",
"IL",
"IT",
"NL",
"SE",
"NO",
"CH",
"AT",
"IE"
],
"countriesToCurrencies": {
"US": "USD",
"CA": "CAD",
"GB": "GBP",
"AF": "USD",
"AX": "USD",
"AL": "USD",
"DZ": "DZD",
"AS": "USD",
"AD": "USD",
"AO": "USD",
"AI": "USD",
"AQ": "USD",
"AG": "USD",
"AR": "ARS",
"AM": "USD",
"AW": "USD",
"AU": "AUD",
"AT": "EUR",
"AZ": "USD",
"BH": "USD",
"BD": "BDT",
"BB": "USD",
"BY": "USD",
"BE": "EUR",
"BZ": "USD",
"BJ": "USD",
"BM": "USD",
"BT": "USD",
"BO": "BOB",
"BQ": "USD",
"BA": "USD",
"BW": "USD",
"BV": "USD",
"BR": "BRL",
"IO": "USD",
"VG": "USD",
"BN": "USD",
"BG": "USD",
"BF": "USD",
"BI": "USD",
"KH": "USD",
"CM": "USD",
"CV": "USD",
"KY": "USD",
"CI": "USD",
"CF": "USD",
"TD": "USD",
"CL": "CLP",
"CN": "CNY",
"CX": "USD",
"CC": "USD",
"CO": "COP",
"KM": "USD",
"CK": "USD",
"CR": "CRC",
"HR": "USD",
"CU": "USD",
"CW": "USD",
"CY": "EUR",
"CZ": "CZK",
"CD": "USD",
"DK": "DKK",
"DJ": "USD",
"DM": "USD",
"DO": "USD",
"EC": "USD",
"EG": "EGP",
"SV": "USD",
"GQ": "USD",
"ER": "USD",
"EE": "EUR",
"ET": "USD",
"FK": "USD",
"FO": "USD",
"FM": "USD",
"FJ": "USD",
"FI": "EUR",
"FR": "EUR",
"GF": "USD",
"PF": "USD",
"TF": "USD",
"GA": "USD",
"GE": "USD",
"DE": "EUR",
"GH": "USD",
"GI": "USD",
"GR": "EUR",
"GL": "USD",
"GD": "USD",
"GP": "USD",
"GU": "USD",
"GT": "GTQ",
"GG": "USD",
"GN": "USD",
"GW": "USD",
"GY": "USD",
"HT": "USD",
"HM": "USD",
"HN": "HNL",
"HK": "HKD",
"HU": "HUF",
"IS": "ISK",
"IN": "INR",
"ID": "IDR",
"IR": "USD",
"IQ": "USD",
"IE": "EUR",
"IM": "USD",
"IL": "ILS",
"IT": "EUR",
"JM": "USD",
"JP": "JPY",
"JE": "USD",
"JO": "USD",
"KZ": "USD",
"KE": "KES",
"KI": "USD",
"XK": "USD",
"KW": "USD",
"KG": "USD",
"LA": "USD",
"LV": "USD",
"LB": "USD",
"LS": "ZAR",
"LR": "USD",
"LY": "USD",
"LI": "USD",
"LT": "USD",
"LU": "EUR",
"MO": "MOP",
"MK": "USD",
"MG": "USD",
"MW": "USD",
"MY": "MYR",
"MV": "USD",
"ML": "USD",
"MT": "EUR",
"MH": "USD",
"MQ": "USD",
"MR": "USD",
"MU": "USD",
"YT": "USD",
"MX": "MXN",
"MD": "USD",
"MC": "EUR",
"MN": "USD",
"ME": "USD",
"MS": "USD",
"MA": "USD",
"MZ": "USD",
"MM": "USD",
"NA": "ZAR",
"NR": "USD",
"NP": "USD",
"NL": "EUR",
"AN": "USD",
"NC": "USD",
"NZ": "NZD",
"NI": "NIO",
"NE": "USD",
"NG": "NGN",
"NU": "USD",
"NF": "USD",
"KP": "USD",
"MP": "USD",
"NO": "NOK",
"OM": "USD",
"PK": "PKR",
"PW": "USD",
"PS": "USD",
"PA": "USD",
"PG": "USD",
"PY": "PYG",
"PE": "PEN",
"PH": "PHP",
"PN": "USD",
"PL": "PLN",
"PT": "EUR",
"PR": "USD",
"QA": "QAR",
"RE": "USD",
"CG": "USD",
"RO": "RON",
"RU": "RUB",
"RW": "USD",
"BL": "USD",
"SH": "USD",
"KN": "USD",
"MF": "USD",
"PM": "USD",
"VC": "USD",
"WS": "USD",
"SM": "USD",
"ST": "USD",
"SA": "SAR",
"SN": "USD",
"RS": "USD",
"SC": "USD",
"SL": "USD",
"SG": "SGD",
"SX": "USD",
"SK": "EUR",
"SI": "EUR",
"SB": "USD",
"SO": "USD",
"ZA": "ZAR",
"GS": "USD",
"KR": "KRW",
"SS": "USD",
"ES": "EUR",
"LK": "USD",
"LC": "USD",
"SD": "USD",
"SR": "USD",
"SJ": "USD",
"SZ": "ZAR",
"SE": "SEK",
"CH": "CHF",
"SY": "USD",
"TW": "TWD",
"TJ": "USD",
"TZ": "USD",
"TH": "THB",
"BS": "USD",
"GM": "USD",
"TL": "USD",
"TG": "USD",
"TK": "USD",
"TO": "USD",
"TT": "USD",
"TN": "USD",
"TR": "TRY",
"TM": "USD",
"TC": "USD",
"TV": "USD",
"UG": "USD",
"UA": "USD",
"AE": "AED",
"UM": "USD",
"UY": "UYU",
"VI": "USD",
"UZ": "USD",
"VU": "USD",
"VA": "USD",
"VE": "VEF",
"VN": "VND",
"WF": "USD",
"EH": "USD",
"YE": "USD",
"ZM": "USD",
"ZW": "USD"
},
"embargoedCountries": [
"SD",
"CU",
"IR",
"SY"
],
"legalDrinkingAges": {
"US": 21,
"CA": 19,
"GB": 18,
"AR": 18,
"AU": 18,
"AT": 18,
"BE": 18,
"BR": 18,
"CL": 18,
"CN": 18,
"CO": 18,
"HR": 18,
"DK": 18,
"DO": 18,
"EG": 0,
"FI": 18,
"FR": 18,
"DE": 18,
"GR": 18,
"HK": 18,
"IN": 25,
"ID": 18,
"IE": 18,
"IL": 18,
"IT": 18,
"JP": 20,
"JO": 18,
"KW": 0,
"LB": 18,
"MY": 18,
"MX": 18,
"NL": 18,
"NZ": 18,
"NG": 18,
"NO": 0,
"PK": 18,
"PA": 18,
"PE": 18,
"PH": 18,
"PL": 18,
"RU": 18,
"SA": 0,
"RS": 18,
"SG": 18,
"ZA": 18,
"KR": 19,
"ES": 18,
"SE": 25,
"CH": 18,
"TW": 18,
"TH": 20,
"TR": 24,
"AE": 0,
"VE": 18,
"PT": 18,
"LU": 18,
"BG": 18,
"CZ": 18,
"SI": 18,
"IS": 20,
"SK": 18,
"LT": 18,
"TT": 18,
"BD": 0,
"LK": 21,
"KE": 18,
"HU": 18,
"MA": 18,
"CY": 18,
"JM": 18,
"EC": 18,
"RO": 18,
"BO": 18,
"GT": 18,
"CR": 18,
"QA": 18,
"SV": 18,
"HN": 18,
"NI": 19,
"PY": 20,
"UY": 18,
"PR": 18,
"BA": 18,
"PS": 18,
"TN": 18,
"BH": 18,
"VN": 18,
"GH": 18,
"MU": 18,
"UA": 18,
"MT": 18,
"BS": 18,
"MV": 18,
"OM": 18,
"MK": 18,
"LV": 18,
"EE": 18,
"IQ": 18,
"DZ": 18,
"AL": 18,
"NP": 18,
"MO": 18,
"ME": 18,
"SN": 18,
"GE": 18,
"BN": 0,
"UG": 18,
"GP": 18,
"BB": 18,
"AZ": 18,
"TZ": 18,
"LY": 18,
"MQ": 18,
"CM": 21,
"BW": 18,
"ET": 18,
"KZ": 18,
"NA": 18,
"MG": 18,
"NC": 18,
"MD": 18,
"FJ": 18,
"BY": 18,
"JE": 18,
"GU": 18,
"YE": 0,
"ZM": 18,
"IM": 18,
"HT": 18,
"KH": 18,
"AW": 18,
"PF": 18,
"AF": 0,
"BM": 18,
"GY": 18,
"AM": 18,
"MW": 18,
"AG": 18,
"RW": 18,
"GG": 18,
"GM": 18,
"FO": 18,
"LC": 18,
"KY": 18,
"BJ": 18,
"AD": 18,
"GD": 18,
"VI": 18,
"BZ": 18,
"VC": 18,
"MN": 18,
"MZ": 18,
"ML": 18,
"AO": 18,
"GF": 18,
"UZ": 18,
"DJ": 18,
"BF": 18,
"MC": 18,
"TG": 18,
"GL": 18,
"GA": 18,
"GI": 18,
"CD": 18,
"KG": 18,
"PG": 18,
"BT": 18,
"KN": 18,
"SZ": 18,
"LS": 18,
"LA": 18,
"LI": 18,
"MP": 18,
"SR": 18,
"SC": 18,
"VG": 18,
"TC": 18,
"DM": 18,
"MR": 18,
"AX": 18,
"SM": 18,
"SL": 18,
"NE": 18,
"CG": 18,
"AI": 18,
"YT": 18,
"CV": 18,
"GN": 18,
"TM": 18,
"BI": 18,
"TJ": 18,
"VU": 18,
"SB": 21,
"ER": 18,
"WS": 18,
"AS": 18,
"FK": 18,
"GQ": 18,
"TO": 18,
"KM": 18,
"PW": 21,
"FM": 21,
"CF": 18,
"SO": 18,
"MH": 18,
"VA": 18,
"TD": 18,
"KI": 18,
"ST": 18,
"TV": 18,
"NR": 18,
"RE": 18,
"LR": 18,
"ZW": 18,
"CI": 18,
"MM": 18,
"AN": 18,
"AQ": 18,
"BQ": 18,
"BV": 18,
"IO": 18,
"CX": 18,
"CC": 18,
"CK": 18,
"CW": 18,
"TF": 18,
"GW": 18,
"HM": 18,
"XK": 18,
"MS": 18,
"NU": 18,
"NF": 18,
"KP": 18,
"PN": 18,
"BL": 18,
"SH": 18,
"MF": 18,
"PM": 18,
"SX": 18,
"GS": 18,
"SS": 18,
"SJ": 18,
"TL": 18,
"TK": 18,
"UM": 18,
"WF": 18,
"EH": 18
}
}
