{
  "/etc/issue.net": "Ubuntu 22.04.1 LTS",
  "antiFeatures": {},
  "apksigner": "/usr/bin/apksigner",
  "archivePolicy0": [],
  "commandLine": [
    "/usr/bin/fdroid update",
    "-c",
    "--pretty"
  ],
  "disabled": [],
  "endTimestamp": 1671533960889,
  "failedBuilds": {},
  "jarsigner": "/opt/hostedtoolcache/Java_Zulu_jdk/17.0.5-8/x64/bin/jarsigner",
  "keytool": "/opt/hostedtoolcache/Java_Zulu_jdk/17.0.5-8/x64/bin/keytool",
  "needsUpdate": [
    "org.fdroid.fdroid"
  ],
  "noPackages": [
    "org.fdroid.fdroid"
  ],
  "noUpdateCheck": [
    "org.fdroid.fdroid"
  ],
  "startTimestamp": 1671533952000,
  "subcommand": "update"
}